{
  "AL": [
    {
      "teamId": 147,
      "abbr": "NYY",
      "name": "New York Yankees",
      "krName": "뉴욕 양키스",
      "league": "AL",
      "division": "East",
      "divisionRank": 2,
      "leagueRank": 2,
      "wins": 49,
      "losses": 39,
      "winningPct": 0.557,
      "gamesBack": 4,
      "wildCardGamesBack": 4.5,
      "runsScored": 426,
      "runsAllowed": 343,
      "runDifferential": 83,
      "streak": "L1",
      "last10": "2-8",
      "wildCardRank": 1,
      "inWildCard": true
    },
    {
      "teamId": 114,
      "abbr": "CLE",
      "name": "Cleveland Guardians",
      "krName": "클리블랜드",
      "league": "AL",
      "division": "Central",
      "divisionRank": 2,
      "leagueRank": 4,
      "wins": 47,
      "losses": 43,
      "winningPct": 0.522,
      "gamesBack": 0,
      "wildCardGamesBack": 1.5,
      "runsScored": 356,
      "runsAllowed": 364,
      "runDifferential": -8,
      "streak": "L1",
      "last10": "6-4",
      "wildCardRank": 2,
      "inWildCard": true
    },
    {
      "teamId": 140,
      "abbr": "TEX",
      "name": "Texas Rangers",
      "krName": "텍사스",
      "league": "AL",
      "division": "West",
      "divisionRank": 2,
      "leagueRank": 6,
      "wins": 45,
      "losses": 44,
      "winningPct": 0.506,
      "gamesBack": 0.5,
      "wildCardGamesBack": 0,
      "runsScored": 364,
      "runsAllowed": 369,
      "runDifferential": -5,
      "streak": "L1",
      "last10": "7-3",
      "wildCardRank": 3,
      "inWildCard": true
    },
    {
      "teamId": 117,
      "abbr": "HOU",
      "name": "Houston Astros",
      "krName": "휴스턴",
      "league": "AL",
      "division": "West",
      "divisionRank": 3,
      "leagueRank": 7,
      "wins": 44,
      "losses": 47,
      "winningPct": 0.484,
      "gamesBack": 2.5,
      "wildCardGamesBack": 2,
      "runsScored": 411,
      "runsAllowed": 457,
      "runDifferential": -46,
      "streak": "W1",
      "last10": "6-4",
      "wildCardRank": 4,
      "inWildCard": false
    },
    {
      "teamId": 142,
      "abbr": "MIN",
      "name": "Minnesota Twins",
      "krName": "미네소타",
      "league": "AL",
      "division": "Central",
      "divisionRank": 3,
      "leagueRank": 8,
      "wins": 43,
      "losses": 47,
      "winningPct": 0.478,
      "gamesBack": 4,
      "wildCardGamesBack": 2.5,
      "runsScored": 442,
      "runsAllowed": 464,
      "runDifferential": -22,
      "streak": "W1",
      "last10": "5-5",
      "wildCardRank": 5,
      "inWildCard": false
    },
    {
      "teamId": 141,
      "abbr": "TOR",
      "name": "Toronto Blue Jays",
      "krName": "토론토",
      "league": "AL",
      "division": "East",
      "divisionRank": 3,
      "leagueRank": 9,
      "wins": 42,
      "losses": 47,
      "winningPct": 0.472,
      "gamesBack": 11.5,
      "wildCardGamesBack": 3,
      "runsScored": 356,
      "runsAllowed": 394,
      "runDifferential": -38,
      "streak": "L1",
      "last10": "3-7",
      "wildCardRank": 6,
      "inWildCard": false
    }
  ],
  "NL": [
    {
      "teamId": 143,
      "abbr": "PHI",
      "name": "Philadelphia Phillies",
      "krName": "필라델피아",
      "league": "NL",
      "division": "East",
      "divisionRank": 2,
      "leagueRank": 4,
      "wins": 50,
      "losses": 39,
      "winningPct": 0.562,
      "gamesBack": 3,
      "wildCardGamesBack": 1.5,
      "runsScored": 400,
      "runsAllowed": 390,
      "runDifferential": 10,
      "streak": "W1",
      "last10": "7-3",
      "wildCardRank": 1,
      "inWildCard": true
    },
    {
      "teamId": 112,
      "abbr": "CHC",
      "name": "Chicago Cubs",
      "krName": "시카고 컵스",
      "league": "NL",
      "division": "Central",
      "divisionRank": 2,
      "leagueRank": 5,
      "wins": 49,
      "losses": 40,
      "winningPct": 0.551,
      "gamesBack": 6,
      "wildCardGamesBack": 0.5,
      "runsScored": 449,
      "runsAllowed": 405,
      "runDifferential": 44,
      "streak": "L2",
      "last10": "7-3",
      "wildCardRank": 2,
      "inWildCard": true
    },
    {
      "teamId": 138,
      "abbr": "STL",
      "name": "St. Louis Cardinals",
      "krName": "세인트루이스",
      "league": "NL",
      "division": "Central",
      "divisionRank": 3,
      "leagueRank": 6,
      "wins": 47,
      "losses": 39,
      "winningPct": 0.547,
      "gamesBack": 6.5,
      "wildCardGamesBack": 0,
      "runsScored": 399,
      "runsAllowed": 384,
      "runDifferential": 15,
      "streak": "W3",
      "last10": "5-5",
      "wildCardRank": 3,
      "inWildCard": true
    },
    {
      "teamId": 146,
      "abbr": "MIA",
      "name": "Miami Marlins",
      "krName": "마이애미",
      "league": "NL",
      "division": "East",
      "divisionRank": 3,
      "leagueRank": 7,
      "wins": 48,
      "losses": 42,
      "winningPct": 0.533,
      "gamesBack": 5.5,
      "wildCardGamesBack": 1,
      "runsScored": 409,
      "runsAllowed": 386,
      "runDifferential": 23,
      "streak": "W2",
      "last10": "7-3",
      "wildCardRank": 4,
      "inWildCard": false
    },
    {
      "teamId": 120,
      "abbr": "WSH",
      "name": "Washington Nationals",
      "krName": "워싱턴",
      "league": "NL",
      "division": "East",
      "divisionRank": 4,
      "leagueRank": 8,
      "wins": 46,
      "losses": 44,
      "winningPct": 0.511,
      "gamesBack": 7.5,
      "wildCardGamesBack": 3,
      "runsScored": 480,
      "runsAllowed": 465,
      "runDifferential": 15,
      "streak": "L1",
      "last10": "5-5",
      "wildCardRank": 5,
      "inWildCard": false
    },
    {
      "teamId": 134,
      "abbr": "PIT",
      "name": "Pittsburgh Pirates",
      "krName": "피츠버그",
      "league": "NL",
      "division": "Central",
      "divisionRank": 4,
      "leagueRank": 9,
      "wins": 45,
      "losses": 45,
      "winningPct": 0.5,
      "gamesBack": 10.5,
      "wildCardGamesBack": 4,
      "runsScored": 464,
      "runsAllowed": 437,
      "runDifferential": 27,
      "streak": "W1",
      "last10": "5-5",
      "wildCardRank": 6,
      "inWildCard": false
    }
  ]
}